rdnoticeshipment/EcsInterface.py
rdnoticeshipment/__init__.py
rdnoticeshipment/mainModel.py
rdnoticeshipment/metadata.py
rdnoticeshipment/operation.py
rdnoticeshipment/utility.py
tests/__init__.py
tests/test_dms_demo.py
rdnoticeshipment-1.2.0.dist-info/METADATA
rdnoticeshipment-1.2.0.dist-info/WHEEL
rdnoticeshipment-1.2.0.dist-info/top_level.txt
rdnoticeshipment-1.2.0.dist-info/RECORD
